{
  "requestsFinished": 0,
  "requestsFailed": 0,
  "requestsRetries": 0,
  "requestsFailedPerMinute": 0,
  "requestsFinishedPerMinute": 0,
  "requestMinDurationMillis": null,
  "requestMaxDurationMillis": 0,
  "requestTotalFailedDurationMillis": 0,
  "requestTotalFinishedDurationMillis": 0,
  "crawlerStartedAt": "2024-05-13T02:50:21.591Z",
  "crawlerFinishedAt": null,
  "statsPersistedAt": "2024-05-13T02:54:21.550Z",
  "crawlerRuntimeMillis": 240187,
  "crawlerLastStartTimestamp": 1715568621363,
  "requestRetryHistogram": [],
  "statsId": 12,
  "requestAvgFailedDurationMillis": null,
  "requestAvgFinishedDurationMillis": null,
  "requestTotalDurationMillis": 0,
  "requestsTotal": 0,
  "requestsWithStatusCode": {
    "502": 2
  },
  "errors": {},
  "retryErrors": {
    "/Users/zhangbo/Desktop/paopao/crawl-international-school/node_modules/.pnpm/@crawlee+http@3.9.2/node_modules/@crawlee/src/internals/http-crawler.ts:685:19": {
      "missing error code": {
        "Error": {
          "502 - Internal Server Error: ": {
            "count": 2
          }
        }
      }
    },
    "/Users/zhangbo/Desktop/paopao/crawl-international-school/node_modules/.pnpm/@apify+timeout@0.3.1/node_modules/@apify/src/index.ts:88:74": {
      "missing error code": {
        "Error": {
          "request timed out after 30 seconds.": {
            "count": 8
          }
        }
      }
    }
  }
}